fim/README.md
fim/__init__.py
fim/pluggable.py
fim/view_only_dict.py
fim/authz/__init__.py
fim/authz/attribute_collector.py
fim/graph/README.md
fim/graph/__init__.py
fim/graph/abc_property_graph.py
fim/graph/abc_property_graph_constants.py
fim/graph/graph_util.py
fim/graph/neo4j_property_graph.py
fim/graph/networkx_mixin.py
fim/graph/networkx_property_graph.py
fim/graph/networkx_property_graph_disjoint.py
fim/graph/typed_tuples.py
fim/graph/data/__init__.py
fim/graph/data/capacity_types.json
fim/graph/data/constraint_types.json
fim/graph/data/graph_validation_rules.json
fim/graph/data/graph_validation_rules_neo4j_v4.json
fim/graph/data/label_types.json
fim/graph/data/location_types.json
fim/graph/data/neo4j_indexes.json
fim/graph/resources/README.md
fim/graph/resources/__init__.py
fim/graph/resources/abc_adm.py
fim/graph/resources/abc_arm.py
fim/graph/resources/abc_bqm.py
fim/graph/resources/abc_cbm.py
fim/graph/resources/neo4j_adm.py
fim/graph/resources/neo4j_arm.py
fim/graph/resources/neo4j_cbm.py
fim/graph/resources/networkx_abqm.py
fim/graph/resources/networkx_adm.py
fim/graph/resources/networkx_arm.py
fim/graph/slices/README.md
fim/graph/slices/__init__.py
fim/graph/slices/abc_asm.py
fim/graph/slices/neo4j_asm.py
fim/graph/slices/networkx_asm.py
fim/logging/__init__.py
fim/logging/fim_logger.py
fim/logging/log_collector.py
fim/slivers/README.md
fim/slivers/__init__.py
fim/slivers/attached_components.py
fim/slivers/base_sliver.py
fim/slivers/capacities_labels.py
fim/slivers/component_catalog.py
fim/slivers/delegations.py
fim/slivers/gateway.py
fim/slivers/identifiers.py
fim/slivers/instance_catalog.py
fim/slivers/interface_info.py
fim/slivers/json.py
fim/slivers/json_data.py
fim/slivers/maintenance_mode.py
fim/slivers/network_attached_storage.py
fim/slivers/network_link.py
fim/slivers/network_node.py
fim/slivers/network_service.py
fim/slivers/path_info.py
fim/slivers/tags.py
fim/slivers/topology_diff.py
fim/slivers/data/__init__.py
fabric_fim-1.9.1.dist-info/entry_points.txt
fabric_fim-1.9.1.dist-info/licenses/LICENSE
fabric_fim-1.9.1.dist-info/WHEEL
fabric_fim-1.9.1.dist-info/METADATA
fabric_fim-1.9.1.dist-info/RECORD
