Metadata-Version: 2.4
Name: fabric_fim
Version: 1.9.1
Summary: FABRIC Information Model library and utilities
Keywords: Neo4j
Author-email: Ilya Baldin <ibaldin@renci.org>
Requires-Python: >=3.9
Classifier: License :: OSI Approved :: MIT License
Classifier: Programming Language :: Python :: 3
Classifier: Operating System :: OS Independent
License-File: LICENSE
Requires-Dist: matplotlib >= 3.6.0
Requires-Dist: neo4j >= 5.3.0
Requires-Dist: networkx >= 3.1
Requires-Dist: networkx-query >= 2.0.0
Requires-Dist: PyYAML >= 6.0
Requires-Dist: recordclass >= 0.17.5
Requires-Dist: requests >= 2.28.1
Requires-Dist: lxml >= 4.9.2
Requires-Dist: pytest ; extra == "test"
Project-URL: Home, https://github.com/fabric-testbed/InformationModel
Provides-Extra: test
